cosmos_guardrail/__init__.py
cosmos_guardrail/cosmos_guardrail.py
cosmos_guardrail/cosmos_utils.py
cosmos_guardrail/utils.py
cosmos_guardrail-0.1.0.dist-info/licenses/LICENSE
cosmos_guardrail-0.1.0.dist-info/METADATA
cosmos_guardrail-0.1.0.dist-info/WHEEL
cosmos_guardrail-0.1.0.dist-info/top_level.txt
cosmos_guardrail-0.1.0.dist-info/RECORD
